seismic_python-0.0.1a0.dist-info/METADATA
seismic_python-0.0.1a0.dist-info/WHEEL
seismic_python-0.0.1a0.dist-info/LICENSE.md
seispy/_io.cp313-win_amd64.pyd
seispy/_io.cp313-win_amd64.lib
seispy/segy.cp313-win_amd64.pyd
seispy/segy.cp313-win_amd64.lib
seispy/synthetics.cp313-win_amd64.pyd
seispy/synthetics.cp313-win_amd64.lib
seispy/filters.cp313-win_amd64.pyd
seispy/filters.cp313-win_amd64.lib
seispy/__init__.py
seispy/plotting.py
seismic_python-0.0.1a0.dist-info/RECORD
