Metadata-Version: 2.1
Name: seismic-python
Version: 0.0.1a0
Summary: Wavefield Imaging
Keywords: SeismicUnix,wavefield,imaging,seismic,gpr
Author-Email: Joseph Capriotti <josephrcapriotti@gmail.com>
License: 
Classifier: Development Status :: 1 - Planning
Classifier: Intended Audience :: Developers
Classifier: Intended Audience :: Science/Research
Classifier: License :: OSI Approved :: MIT License
Classifier: Programming Language :: Python
Classifier: Programming Language :: Cython
Classifier: Programming Language :: C
Classifier: Topic :: Scientific/Engineering
Classifier: Topic :: Scientific/Engineering :: Mathematics
Classifier: Topic :: Scientific/Engineering :: Physics
Classifier: Operating System :: Microsoft :: Windows
Classifier: Operating System :: POSIX
Classifier: Operating System :: Unix
Classifier: Operating System :: MacOS
Classifier: Natural Language :: English
Project-URL: Homepage, http://github.com/jcapriot/seismic-python
Project-URL: Repository, http://github.com/jcapriot/seismic-python.git
Requires-Python: >=3.10
Requires-Dist: numpy>=1.22.4
Requires-Dist: matplotlib
